{
  "ontologyId": "obi",
  "parentIri": "obo:OBI_0002106",
  "children": [
    {
      "iri": "obo:OBI_0002096",
      "label": "carboxyfluorescein succinimidyl ester staining assay measuring epitope specific proliferation of T cells",
      "hasChildren": false,
      "childrenKey": "60b3f360c800dc894906bc3f1e8187d0b98bc29e"
    },
    {
      "iri": "obo:OBI_0003582",
      "label": "cell proliferation assay using carboxyfluorescein succinimidyl ester staining",
      "hasChildren": false,
      "childrenKey": "c29a9982f9655071f1aaca1338f5c4ba059e1569"
    }
  ]
}
